adk/ADK.py
adk/__init__.py
adk/classes.py
adk/io.py
adk/mlops.py
adk/modeldata.py
algorithmia_adk-1.2.4.dist-info/LICENSE
algorithmia_adk-1.2.4.dist-info/METADATA
algorithmia_adk-1.2.4.dist-info/WHEEL
algorithmia_adk-1.2.4.dist-info/top_level.txt
algorithmia_adk-1.2.4.dist-info/RECORD
